odoo/addons/ssi_stock_balance/README.rst
odoo/addons/ssi_stock_balance/__init__.py
odoo/addons/ssi_stock_balance/__manifest__.py
odoo/addons/ssi_stock_balance/menu.xml
odoo/addons/ssi_stock_balance/data/approval_template_data.xml
odoo/addons/ssi_stock_balance/data/base_automation_data.xml
odoo/addons/ssi_stock_balance/data/ir_actions_server_data.xml
odoo/addons/ssi_stock_balance/data/ir_sequence_data.xml
odoo/addons/ssi_stock_balance/data/policy_template_data.xml
odoo/addons/ssi_stock_balance/data/sequence_template_data.xml
odoo/addons/ssi_stock_balance/i18n/ssi_stock_balance.pot
odoo/addons/ssi_stock_balance/models/__init__.py
odoo/addons/ssi_stock_balance/models/product_product.py
odoo/addons/ssi_stock_balance/models/product_stock_balance.py
odoo/addons/ssi_stock_balance/models/stock_balance.py
odoo/addons/ssi_stock_balance/models/stock_balance_type.py
odoo/addons/ssi_stock_balance/models/stock_move.py
odoo/addons/ssi_stock_balance/security/ir.model.access.csv
odoo/addons/ssi_stock_balance/security/ir_module_category_data.xml
odoo/addons/ssi_stock_balance/security/ir_rule_data.xml
odoo/addons/ssi_stock_balance/security/res_group_data.xml
odoo/addons/ssi_stock_balance/static/description/icon.png
odoo/addons/ssi_stock_balance/views/product_product_views.xml
odoo/addons/ssi_stock_balance/views/product_stock_balance_picking_views.xml
odoo/addons/ssi_stock_balance/views/product_stock_balance_views.xml
odoo/addons/ssi_stock_balance/views/product_stock_balance_warehouse_views.xml
odoo/addons/ssi_stock_balance/views/stock_balance_type_views.xml
odoo/addons/ssi_stock_balance/views/stock_balance_views.xml
odoo14_addon_ssi_stock_balance-14.0.1.8.1.dist-info/METADATA
odoo14_addon_ssi_stock_balance-14.0.1.8.1.dist-info/WHEEL
odoo14_addon_ssi_stock_balance-14.0.1.8.1.dist-info/top_level.txt
odoo14_addon_ssi_stock_balance-14.0.1.8.1.dist-info/RECORD
